{
    "lewels": {
        "Horror": {
            "*": 8,
            "@": 8,
            "Rec": 1,
            "muve": 3,
            "saiz": 20,
            "wall": true
        },
        "lev": {
            "*": 2,
            "@": 5,
            "Rec": 8,
            "muve": 1,
            "saiz": 5,
            "wall": false
        },
        "lev1": {
            "*": 1,
            "@": 1,
            "muve": 2,
            "saiz": 5,
            "wall": true
        }
    },
    "record": {
        "easyRec": 1,
        "hardRec": 3,
        "normalRec": 2
    }
}